OSL_ANALYSIS/E_values.py
OSL_ANALYSIS/__init__.py
OSL_ANALYSIS/download.py
OSL_ANALYSIS/modulo1.py
OSL_ANALYSIS/modulo2.py
OSL_ANALYSIS/modulo3.py
OSL_ANALYSIS/modulo4.py
osl_analysis-0.1.20.dist-info/METADATA
osl_analysis-0.1.20.dist-info/WHEEL
osl_analysis-0.1.20.dist-info/top_level.txt
osl_analysis-0.1.20.dist-info/RECORD
