Metadata-Version: 2.1
Name: osl-analysis
Version: 0.1.20
Summary: program for the analysis of physical processes of OSL curves
Home-page: https://pypi.org/project/OSL_ANALYSIS/
Author: EDWIN JOEL PILCO QUISPE
Author-email: edwinpilco10@gmail.com
Classifier: Programming Language :: Python :: 3
Classifier: License :: OSI Approved :: MIT License
Classifier: Operating System :: OS Independent
Classifier: Intended Audience :: Science/Research
Classifier: Topic :: Scientific/Engineering
Requires-Python: >=3.6
Requires-Dist: numpy
Requires-Dist: matplotlib
Requires-Dist: scipy
Requires-Dist: pandas
Requires-Dist: prettytable
Requires-Dist: ipython
